dask_glm/__init__.py
dask_glm/algorithms.py
dask_glm/datasets.py
dask_glm/estimators.py
dask_glm/families.py
dask_glm/regularizers.py
dask_glm/utils.py
dask_glm-0.3.2.dist-info/LICENSE.txt
dask_glm-0.3.2.dist-info/METADATA
dask_glm-0.3.2.dist-info/WHEEL
dask_glm-0.3.2.dist-info/top_level.txt
dask_glm-0.3.2.dist-info/RECORD
