Metadata-Version: 2.1
Name: dask-glm
Version: 0.3.2
Summary: Generalized Linear Models with Dask
Home-page: http://github.com/dask/dask-glm/
Maintainer: Matthew Rocklin
Maintainer-email: mrocklin@gmail.com
License: BSD
Keywords: dask,glm
Provides-Extra: docs
License-File: LICENSE.txt
